MohamedSataryAnotherLibraryTryOut/__init__.py
MohamedSataryAnotherLibraryTryOut/anotherOne.py
MohamedSataryAnotherLibraryTryOut-0.0.1.dist-info/METADATA
MohamedSataryAnotherLibraryTryOut-0.0.1.dist-info/WHEEL
MohamedSataryAnotherLibraryTryOut-0.0.1.dist-info/top_level.txt
MohamedSataryAnotherLibraryTryOut-0.0.1.dist-info/RECORD
