Metadata-Version: 2.1
Name: MohamedSataryAnotherLibraryTryOut
Version: 0.0.1
Summary: This library converts Names (or words) from arabic to its 
